setup.py
rmbTrans/__init__.py
rmbTrans.egg-info/PKG-INFO
rmbTrans.egg-info/SOURCES.txt
rmbTrans.egg-info/dependency_links.txt
rmbTrans.egg-info/top_level.txt