Metadata-Version: 1.0
Name: rmbTrans
Version: 0.1.0
Summary: 中文金额转阿拉伯数字
Home-page: https://wsgfz.cn
Author: wsgfz
Author-email: wsgfz.cn@gmail.com
License: UNKNOWN
Platform: UNKNOWN
